scrapy_item-0.0.3-py3.7-nspkg.pth
alexber/scrapyitem/__init__.py
alexber/scrapyitem/data/__init__.py
tests_data/__init__.py
tests_data/tests/__init__.py
scrapy_item-0.0.3.dist-info/LICENSE.txt
scrapy_item-0.0.3.dist-info/METADATA
scrapy_item-0.0.3.dist-info/WHEEL
scrapy_item-0.0.3.dist-info/namespace_packages.txt
scrapy_item-0.0.3.dist-info/top_level.txt
scrapy_item-0.0.3.dist-info/RECORD
